django_multi_bulk_updater/__init__.py
django_multi_bulk_updater/parallelExcecutor.py
django_multi_bulk_updater/queryChunking.py
django_multi_bulk_updater/queryConvertor.py
django_multi_bulk_updater-1.0.3.dist-info/LICENCE
django_multi_bulk_updater-1.0.3.dist-info/METADATA
django_multi_bulk_updater-1.0.3.dist-info/WHEEL
django_multi_bulk_updater-1.0.3.dist-info/top_level.txt
django_multi_bulk_updater-1.0.3.dist-info/RECORD
